MANIFEST.in
README
setup.py
bash_completion/git-devbliss
git_devbliss/__init__.py
git_devbliss/__main__.py
git_devbliss.egg-info/PKG-INFO
git_devbliss.egg-info/SOURCES.txt
git_devbliss.egg-info/dependency_links.txt
git_devbliss.egg-info/entry_points.txt
git_devbliss.egg-info/requires.txt
git_devbliss.egg-info/top_level.txt
git_devbliss/github/__init__.py
git_devbliss/github/__main__.py
git_devbliss/github/tests/__init__.py
git_devbliss/github/tests/test_init.py
git_devbliss/github/tests/test_main.py
git_devbliss/tests/__init__.py
git_devbliss/tests/test_dist.py
git_devbliss/tests/test_main.py
man1/git-devbliss.1