Metadata-Version: 1.1
Name: git-devbliss
Version: 2.0.5
Summary: Tool supporting the devbliss Git/GitHub Workflow
Home-page: http://www.devbliss.com
Author: devbliss GmbH
Author-email: python_maintainer@devbliss.com
License: Apache2
Download-URL: https://github.com/devbliss/git-devbliss
Platform: UNKNOWN
Classifier: Development Status :: 5 - Production/Stable
Classifier: Environment :: Console
Classifier: Intended Audience :: Developers
Classifier: Intended Audience :: End Users/Desktop
Classifier: Intended Audience :: System Administrators
Classifier: License :: OSI Approved :: Apache Software License
Classifier: Natural Language :: English
Classifier: Operating System :: MacOS :: MacOS X
Classifier: Operating System :: Microsoft :: Windows
Classifier: Operating System :: POSIX
Classifier: Programming Language :: Python :: 3.4
Classifier: Topic :: Software Development :: Version Control
Classifier: Topic :: Utilities
